metalake_management/__init__.py
metalake_management/adls_management/__init__.py
metalake_management/adls_management/connection.py
metalake_management/adls_management/folder_management.py
metalake_management/batch_process_phases/__init__.py
metalake_management/batch_process_phases/from_to_phase.py
metalake_management/interface_file_management/__init__.py
metalake_management/interface_file_management/interface_file_handling.py
metalake_management/utils/__init__.py
metalake_management/utils/messages.py
metalake_management/utils/settings.py
plugins/__init__.py
src/__init__.py
src/adls_management/__init__.py
src/adls_management/connection.py
src/adls_management/folder_management.py
src/adls_management/messages.py
src/batch_process_phases/__init__.py
src/batch_process_phases/from_to_phase.py
src/interface_file_management/__init__.py
src/interface_file_management/interface_file_handling.py
src/utils/__init__.py
src/utils/messages.py
src/utils/settings.py
tests/__init__.py
tests/test_create_folder.py
metalake_file_management-0.1.7.dist-info/LICENSE
metalake_file_management-0.1.7.dist-info/METADATA
metalake_file_management-0.1.7.dist-info/WHEEL
metalake_file_management-0.1.7.dist-info/top_level.txt
metalake_file_management-0.1.7.dist-info/RECORD
